cdwutils/__init__.py
cdwutils/__version__.py
cdwutils/aws/__init__.py
cdwutils/aws/common.py
cdwutils/aws/s3.py
cdwutils/aws/secrets_manager.py
cdwutils/comms.py
cdwutils/databricks.py
cdwutils/datadomains/__init__.py
cdwutils/datadomains/behavioural.py
cdwutils/datadomains/brand_providers.py
cdwutils/datadomains/common.py
cdwutils/datadomains/content.py
cdwutils/datadomains/dimension_keys.py
cdwutils/etl.py
cdwutils/exceptions.py
cdwutils/gsheets.py
cdwutils/misc.py
cdwutils/snowflake.py
cdwutils/spark_extensions.py
cdwutils-1.13.29.dist-info/WHEEL
cdwutils-1.13.29.dist-info/METADATA
cdwutils-1.13.29.dist-info/RECORD
