Metadata-Version: 2.1
Name: cdwutils
Version: 1.13.29
Summary: Common utils for CDW jobs.
Home-page: https://github.schibsted.io/analytical-foundations/cdw-utils
Author: Common Data Warehouse team
Author-email: dt-analytics-cdwc@schibsted.com
Requires-Python: >=3.8,<3.11
Classifier: Programming Language :: Python :: 3
Classifier: Programming Language :: Python :: 3.10
Classifier: Programming Language :: Python :: 3.8
Classifier: Programming Language :: Python :: 3.9
Requires-Dist: boto3 (>=1.18.55,<2.0.0)
Requires-Dist: gspread (>=5.2.0,<6.0.0)
Requires-Dist: slackclient (>=2.9.3,<3.0.0)
Requires-Dist: snowflake-connector-python (>=2.6.2,<3.0.0)
